{"modules": [{"id": "codemarp.analyzers.high_level", "path": "codemarp/analyzers/high_level.py", "package": "codemarp.analyzers", "language": "python"}, {"id": "codemarp.analyzers.low_level", "path": "codemarp/analyzers/low_level.py", "package": "codemarp.analyzers", "language": "python"}, {"id": "codemarp.analyzers.mid_level", "path": "codemarp/analyzers/mid_level.py", "package": "codemarp.analyzers", "language": "python"}, {"id": "codemarp.cli.main", "path": "codemarp/cli/main.py", "package": "codemarp.cli", "language": "python"}, {"id": "codemarp.contracts", "path": "codemarp/contracts.py", "package": "codemarp", "language": "python"}, {"id": "codemarp.errors", "path": "codemarp/errors.py", "package": "codemarp", "language": "python"}, {"id": "codemarp.exporters.json_exporter", "path": "codemarp/exporters/json_exporter.py", "package": "codemarp.exporters", "language": "python"}, {"id": "codemarp.exporters.mermaid", "path": "codemarp/exporters/mermaid.py", "package": "codemarp.exporters", "language": "python"}, {"id": "codemarp.graph.builder", "path": "codemarp/graph/builder.py", "package": "codemarp.graph", "language": "python"}, {"id": "codemarp.graph.models", "path": "codemarp/graph/models.py", "package": "codemarp.graph", "language": "python"}, {"id": "codemarp.parser.contracts", "path": "codemarp/parser/contracts.py", "package": "codemarp.parser", "language": "python"}, {"id": "codemarp.parser.js_parser", "path": "codemarp/parser/js_parser.py", "package": "codemarp.parser", "language": "python"}, {"id": "codemarp.parser.python_parser", "path": "codemarp/parser/python_parser.py", "package": "codemarp.parser", "language": "python"}, {"id": "codemarp.pipeline.apply_view", "path": "codemarp/pipeline/apply_view.py", "package": "codemarp.pipeline", "language": "python"}, {"id": "codemarp.pipeline.build_bundle", "path": "codemarp/pipeline/build_bundle.py", "package": "codemarp.pipeline", "language": "python"}, {"id": "codemarp.pipeline.export_all", "path": "codemarp/pipeline/export_all.py", "package": "codemarp.pipeline", "language": "python"}, {"id": "codemarp.views.module_view", "path": "codemarp/views/module_view.py", "package": "codemarp.views", "language": "python"}, {"id": "codemarp.views.subgraph", "path": "codemarp/views/subgraph.py", "package": "codemarp.views", "language": "python"}, {"id": "codemarp.views.trace", "path": "codemarp/views/trace.py", "package": "codemarp.views", "language": "python"}], "functions": [{"id": "codemarp.analyzers.high_level:_dedupe_edges", "module_id": "codemarp.analyzers.high_level", "name": "_dedupe_edges", "lineno": 80, "end_lineno": 88, "class_name": null}, {"id": "codemarp.analyzers.high_level:_resolve_local_import", "module_id": "codemarp.analyzers.high_level", "name": "_resolve_local_import", "lineno": 58, "end_lineno": 77, "class_name": null}, {"id": "codemarp.analyzers.high_level:aggregate_module_id", "module_id": "codemarp.analyzers.high_level", "name": "aggregate_module_id", "lineno": 42, "end_lineno": 55, "class_name": null}, {"id": "codemarp.analyzers.high_level:build_high_level_edges", "module_id": "codemarp.analyzers.high_level", "name": "build_high_level_edges", "lineno": 5, "end_lineno": 39, "class_name": null}, {"id": "codemarp.analyzers.low_level:ControlFlowBuilder.__init__", "module_id": "codemarp.analyzers.low_level", "name": "ControlFlowBuilder.__init__", "lineno": 24, "end_lineno": 27, "class_name": "ControlFlowBuilder"}, {"id": "codemarp.analyzers.low_level:ControlFlowBuilder._add_edge", "module_id": "codemarp.analyzers.low_level", "name": "ControlFlowBuilder._add_edge", "lineno": 288, "end_lineno": 296, "class_name": "ControlFlowBuilder"}, {"id": "codemarp.analyzers.low_level:ControlFlowBuilder._call_label", "module_id": "codemarp.analyzers.low_level", "name": "ControlFlowBuilder._call_label", "lineno": 236, "end_lineno": 245, "class_name": "ControlFlowBuilder"}, {"id": "codemarp.analyzers.low_level:ControlFlowBuilder._callable_name", "module_id": "codemarp.analyzers.low_level", "name": "ControlFlowBuilder._callable_name", "lineno": 247, "end_lineno": 273, "class_name": "ControlFlowBuilder"}, {"id": "codemarp.analyzers.low_level:ControlFlowBuilder._compact_arg_label", "module_id": "codemarp.analyzers.low_level", "name": "ControlFlowBuilder._compact_arg_label", "lineno": 310, "end_lineno": 322, "class_name": "ControlFlowBuilder"}, {"id": "codemarp.analyzers.low_level:ControlFlowBuilder._compact_text", "module_id": "codemarp.analyzers.low_level", "name": "ControlFlowBuilder._compact_text", "lineno": 304, "end_lineno": 308, "class_name": "ControlFlowBuilder"}, {"id": "codemarp.analyzers.low_level:ControlFlowBuilder._expr_label", "module_id": "codemarp.analyzers.low_level", "name": "ControlFlowBuilder._expr_label", "lineno": 216, "end_lineno": 234, "class_name": "ControlFlowBuilder"}, {"id": "codemarp.analyzers.low_level:ControlFlowBuilder._handle_if", "module_id": "codemarp.analyzers.low_level", "name": "ControlFlowBuilder._handle_if", "lineno": 111, "end_lineno": 155, "class_name": "ControlFlowBuilder"}, {"id": "codemarp.analyzers.low_level:ControlFlowBuilder._handle_loop", "module_id": "codemarp.analyzers.low_level", "name": "ControlFlowBuilder._handle_loop", "lineno": 157, "end_lineno": 181, "class_name": "ControlFlowBuilder"}, {"id": "codemarp.analyzers.low_level:ControlFlowBuilder._handle_statement", "module_id": "codemarp.analyzers.low_level", "name": "ControlFlowBuilder._handle_statement", "lineno": 56, "end_lineno": 87, "class_name": "ControlFlowBuilder"}, {"id": "codemarp.analyzers.low_level:ControlFlowBuilder._new_node", "module_id": "codemarp.analyzers.low_level", "name": "ControlFlowBuilder._new_node", "lineno": 275, "end_lineno": 286, "class_name": "ControlFlowBuilder"}, {"id": "codemarp.analyzers.low_level:ControlFlowBuilder._node_kind", "module_id": "codemarp.analyzers.low_level", "name": "ControlFlowBuilder._node_kind", "lineno": 298, "end_lineno": 302, "class_name": "ControlFlowBuilder"}, {"id": "codemarp.analyzers.low_level:ControlFlowBuilder._statement_label", "module_id": "codemarp.analyzers.low_level", "name": "ControlFlowBuilder._statement_label", "lineno": 183, "end_lineno": 214, "class_name": "ControlFlowBuilder"}, {"id": "codemarp.analyzers.low_level:ControlFlowBuilder._walk_branch_statements", "module_id": "codemarp.analyzers.low_level", "name": "ControlFlowBuilder._walk_branch_statements", "lineno": 89, "end_lineno": 109, "class_name": "ControlFlowBuilder"}, {"id": "codemarp.analyzers.low_level:ControlFlowBuilder._walk_statements", "module_id": "codemarp.analyzers.low_level", "name": "ControlFlowBuilder._walk_statements", "lineno": 46, "end_lineno": 54, "class_name": "ControlFlowBuilder"}, {"id": "codemarp.analyzers.low_level:ControlFlowBuilder.build_for_function", "module_id": "codemarp.analyzers.low_level", "name": "ControlFlowBuilder.build_for_function", "lineno": 29, "end_lineno": 44, "class_name": "ControlFlowBuilder"}, {"id": "codemarp.analyzers.low_level:build_low_level_view", "module_id": "codemarp.analyzers.low_level", "name": "build_low_level_view", "lineno": 16, "end_lineno": 20, "class_name": null}, {"id": "codemarp.analyzers.mid_level:_dedupe_edges", "module_id": "codemarp.analyzers.mid_level", "name": "_dedupe_edges", "lineno": 178, "end_lineno": 186, "class_name": null}, {"id": "codemarp.analyzers.mid_level:_is_dotted_call", "module_id": "codemarp.analyzers.mid_level", "name": "_is_dotted_call", "lineno": 174, "end_lineno": 175, "class_name": null}, {"id": "codemarp.analyzers.mid_level:_resolve_callee", "module_id": "codemarp.analyzers.mid_level", "name": "_resolve_callee", "lineno": 45, "end_lineno": 92, "class_name": null}, {"id": "codemarp.analyzers.mid_level:_resolve_imported_module_call", "module_id": "codemarp.analyzers.mid_level", "name": "_resolve_imported_module_call", "lineno": 134, "end_lineno": 154, "class_name": null}, {"id": "codemarp.analyzers.mid_level:_resolve_imported_symbol_call", "module_id": "codemarp.analyzers.mid_level", "name": "_resolve_imported_symbol_call", "lineno": 104, "end_lineno": 131, "class_name": null}, {"id": "codemarp.analyzers.mid_level:_resolve_same_module_call", "module_id": "codemarp.analyzers.mid_level", "name": "_resolve_same_module_call", "lineno": 95, "end_lineno": 101, "class_name": null}, {"id": "codemarp.analyzers.mid_level:_resolve_unique_global_call", "module_id": "codemarp.analyzers.mid_level", "name": "_resolve_unique_global_call", "lineno": 157, "end_lineno": 171, "class_name": null}, {"id": "codemarp.analyzers.mid_level:build_mid_level_edges", "module_id": "codemarp.analyzers.mid_level", "name": "build_mid_level_edges", "lineno": 6, "end_lineno": 42, "class_name": null}, {"id": "codemarp.cli.main:_validate_analyze_args", "module_id": "codemarp.cli.main", "name": "_validate_analyze_args", "lineno": 122, "end_lineno": 161, "class_name": null}, {"id": "codemarp.cli.main:analyze_command", "module_id": "codemarp.cli.main", "name": "analyze_command", "lineno": 12, "end_lineno": 80, "class_name": null}, {"id": "codemarp.cli.main:build_parser", "module_id": "codemarp.cli.main", "name": "build_parser", "lineno": 83, "end_lineno": 119, "class_name": null}, {"id": "codemarp.cli.main:main", "module_id": "codemarp.cli.main", "name": "main", "lineno": 164, "end_lineno": 181, "class_name": null}, {"id": "codemarp.exporters.json_exporter:export_bundle_json", "module_id": "codemarp.exporters.json_exporter", "name": "export_bundle_json", "lineno": 7, "end_lineno": 9, "class_name": null}, {"id": "codemarp.exporters.mermaid:_collapsed_group_ids", "module_id": "codemarp.exporters.mermaid", "name": "_collapsed_group_ids", "lineno": 67, "end_lineno": 73, "class_name": null}, {"id": "codemarp.exporters.mermaid:_low_level_class_for_kind", "module_id": "codemarp.exporters.mermaid", "name": "_low_level_class_for_kind", "lineno": 117, "end_lineno": 124, "class_name": null}, {"id": "codemarp.exporters.mermaid:_safe_id", "module_id": "codemarp.exporters.mermaid", "name": "_safe_id", "lineno": 76, "end_lineno": 77, "class_name": null}, {"id": "codemarp.exporters.mermaid:_shape_for_kind", "module_id": "codemarp.exporters.mermaid", "name": "_shape_for_kind", "lineno": 80, "end_lineno": 85, "class_name": null}, {"id": "codemarp.exporters.mermaid:export_control_flow", "module_id": "codemarp.exporters.mermaid", "name": "export_control_flow", "lineno": 53, "end_lineno": 64, "class_name": null}, {"id": "codemarp.exporters.mermaid:export_function_graph", "module_id": "codemarp.exporters.mermaid", "name": "export_function_graph", "lineno": 29, "end_lineno": 50, "class_name": null}, {"id": "codemarp.exporters.mermaid:export_low_level_graph", "module_id": "codemarp.exporters.mermaid", "name": "export_low_level_graph", "lineno": 88, "end_lineno": 114, "class_name": null}, {"id": "codemarp.exporters.mermaid:export_module_graph", "module_id": "codemarp.exporters.mermaid", "name": "export_module_graph", "lineno": 5, "end_lineno": 26, "class_name": null}, {"id": "codemarp.graph.builder:GraphBuilder.__init__", "module_id": "codemarp.graph.builder", "name": "GraphBuilder.__init__", "lineno": 11, "end_lineno": 12, "class_name": "GraphBuilder"}, {"id": "codemarp.graph.builder:GraphBuilder.add_control_flow_node", "module_id": "codemarp.graph.builder", "name": "GraphBuilder.add_control_flow_node", "lineno": 26, "end_lineno": 27, "class_name": "GraphBuilder"}, {"id": "codemarp.graph.builder:GraphBuilder.add_control_flow_nodes", "module_id": "codemarp.graph.builder", "name": "GraphBuilder.add_control_flow_nodes", "lineno": 29, "end_lineno": 30, "class_name": "GraphBuilder"}, {"id": "codemarp.graph.builder:GraphBuilder.add_edge", "module_id": "codemarp.graph.builder", "name": "GraphBuilder.add_edge", "lineno": 32, "end_lineno": 33, "class_name": "GraphBuilder"}, {"id": "codemarp.graph.builder:GraphBuilder.add_edges", "module_id": "codemarp.graph.builder", "name": "GraphBuilder.add_edges", "lineno": 35, "end_lineno": 36, "class_name": "GraphBuilder"}, {"id": "codemarp.graph.builder:GraphBuilder.add_function", "module_id": "codemarp.graph.builder", "name": "GraphBuilder.add_function", "lineno": 20, "end_lineno": 21, "class_name": "GraphBuilder"}, {"id": "codemarp.graph.builder:GraphBuilder.add_functions", "module_id": "codemarp.graph.builder", "name": "GraphBuilder.add_functions", "lineno": 23, "end_lineno": 24, "class_name": "GraphBuilder"}, {"id": "codemarp.graph.builder:GraphBuilder.add_module", "module_id": "codemarp.graph.builder", "name": "GraphBuilder.add_module", "lineno": 14, "end_lineno": 15, "class_name": "GraphBuilder"}, {"id": "codemarp.graph.builder:GraphBuilder.add_modules", "module_id": "codemarp.graph.builder", "name": "GraphBuilder.add_modules", "lineno": 17, "end_lineno": 18, "class_name": "GraphBuilder"}, {"id": "codemarp.graph.builder:GraphBuilder.build", "module_id": "codemarp.graph.builder", "name": "GraphBuilder.build", "lineno": 38, "end_lineno": 39, "class_name": "GraphBuilder"}, {"id": "codemarp.graph.models:GraphBundle.edges_by_kind", "module_id": "codemarp.graph.models", "name": "GraphBundle.edges_by_kind", "lineno": 82, "end_lineno": 83, "class_name": "GraphBundle"}, {"id": "codemarp.graph.models:GraphBundle.function_by_id", "module_id": "codemarp.graph.models", "name": "GraphBundle.function_by_id", "lineno": 76, "end_lineno": 80, "class_name": "GraphBundle"}, {"id": "codemarp.graph.models:GraphBundle.functions_in_module", "module_id": "codemarp.graph.models", "name": "GraphBundle.functions_in_module", "lineno": 67, "end_lineno": 68, "class_name": "GraphBundle"}, {"id": "codemarp.graph.models:GraphBundle.module_by_id", "module_id": "codemarp.graph.models", "name": "GraphBundle.module_by_id", "lineno": 70, "end_lineno": 74, "class_name": "GraphBundle"}, {"id": "codemarp.graph.models:GraphBundle.to_dict", "module_id": "codemarp.graph.models", "name": "GraphBundle.to_dict", "lineno": 51, "end_lineno": 65, "class_name": "GraphBundle"}, {"id": "codemarp.parser.js_parser:JavaScriptParser.parse_code", "module_id": "codemarp.parser.js_parser", "name": "JavaScriptParser.parse_code", "lineno": 2, "end_lineno": 3, "class_name": "JavaScriptParser"}, {"id": "codemarp.parser.python_parser:PythonParser.__init__", "module_id": "codemarp.parser.python_parser", "name": "PythonParser.__init__", "lineno": 62, "end_lineno": 64, "class_name": "PythonParser"}, {"id": "codemarp.parser.python_parser:PythonParser._make_call_fact", "module_id": "codemarp.parser.python_parser", "name": "PythonParser._make_call_fact", "lineno": 261, "end_lineno": 311, "class_name": "PythonParser"}, {"id": "codemarp.parser.python_parser:PythonParser._reset_state", "module_id": "codemarp.parser.python_parser", "name": "PythonParser._reset_state", "lineno": 66, "end_lineno": 79, "class_name": "PythonParser"}, {"id": "codemarp.parser.python_parser:PythonParser._resolve_call_name", "module_id": "codemarp.parser.python_parser", "name": "PythonParser._resolve_call_name", "lineno": 233, "end_lineno": 259, "class_name": "PythonParser"}, {"id": "codemarp.parser.python_parser:PythonParser._visit_function_like", "module_id": "codemarp.parser.python_parser", "name": "PythonParser._visit_function_like", "lineno": 191, "end_lineno": 231, "class_name": "PythonParser"}, {"id": "codemarp.parser.python_parser:PythonParser.parse_code", "module_id": "codemarp.parser.python_parser", "name": "PythonParser.parse_code", "lineno": 81, "end_lineno": 99, "class_name": "PythonParser"}, {"id": "codemarp.parser.python_parser:PythonParser.parse_code_to_facts", "module_id": "codemarp.parser.python_parser", "name": "PythonParser.parse_code_to_facts", "lineno": 101, "end_lineno": 116, "class_name": "PythonParser"}, {"id": "codemarp.parser.python_parser:PythonParser.visit_AsyncFunctionDef", "module_id": "codemarp.parser.python_parser", "name": "PythonParser.visit_AsyncFunctionDef", "lineno": 174, "end_lineno": 175, "class_name": "PythonParser"}, {"id": "codemarp.parser.python_parser:PythonParser.visit_Call", "module_id": "codemarp.parser.python_parser", "name": "PythonParser.visit_Call", "lineno": 177, "end_lineno": 189, "class_name": "PythonParser"}, {"id": "codemarp.parser.python_parser:PythonParser.visit_ClassDef", "module_id": "codemarp.parser.python_parser", "name": "PythonParser.visit_ClassDef", "lineno": 166, "end_lineno": 169, "class_name": "PythonParser"}, {"id": "codemarp.parser.python_parser:PythonParser.visit_FunctionDef", "module_id": "codemarp.parser.python_parser", "name": "PythonParser.visit_FunctionDef", "lineno": 171, "end_lineno": 172, "class_name": "PythonParser"}, {"id": "codemarp.parser.python_parser:PythonParser.visit_Import", "module_id": "codemarp.parser.python_parser", "name": "PythonParser.visit_Import", "lineno": 118, "end_lineno": 137, "class_name": "PythonParser"}, {"id": "codemarp.parser.python_parser:PythonParser.visit_ImportFrom", "module_id": "codemarp.parser.python_parser", "name": "PythonParser.visit_ImportFrom", "lineno": 139, "end_lineno": 164, "class_name": "PythonParser"}, {"id": "codemarp.parser.python_parser:_find_function_in_tree", "module_id": "codemarp.parser.python_parser", "name": "_find_function_in_tree", "lineno": 396, "end_lineno": 424, "class_name": null}, {"id": "codemarp.parser.python_parser:discover_python_files", "module_id": "codemarp.parser.python_parser", "name": "discover_python_files", "lineno": 314, "end_lineno": 322, "class_name": null}, {"id": "codemarp.parser.python_parser:find_function_node", "module_id": "codemarp.parser.python_parser", "name": "find_function_node", "lineno": 367, "end_lineno": 393, "class_name": null}, {"id": "codemarp.parser.python_parser:module_id_from_path", "module_id": "codemarp.parser.python_parser", "name": "module_id_from_path", "lineno": 325, "end_lineno": 330, "class_name": null}, {"id": "codemarp.parser.python_parser:package_from_module_id", "module_id": "codemarp.parser.python_parser", "name": "package_from_module_id", "lineno": 333, "end_lineno": 336, "class_name": null}, {"id": "codemarp.parser.python_parser:parse_low_level_focus", "module_id": "codemarp.parser.python_parser", "name": "parse_low_level_focus", "lineno": 346, "end_lineno": 364, "class_name": null}, {"id": "codemarp.parser.python_parser:parse_python_file", "module_id": "codemarp.parser.python_parser", "name": "parse_python_file", "lineno": 339, "end_lineno": 343, "class_name": null}, {"id": "codemarp.pipeline.apply_view:apply_view", "module_id": "codemarp.pipeline.apply_view", "name": "apply_view", "lineno": 16, "end_lineno": 40, "class_name": null}, {"id": "codemarp.pipeline.build_bundle:build_bundle", "module_id": "codemarp.pipeline.build_bundle", "name": "build_bundle", "lineno": 24, "end_lineno": 66, "class_name": null}, {"id": "codemarp.pipeline.export_all:export_all", "module_id": "codemarp.pipeline.export_all", "name": "export_all", "lineno": 19, "end_lineno": 44, "class_name": null}, {"id": "codemarp.pipeline.export_all:export_low_level", "module_id": "codemarp.pipeline.export_all", "name": "export_low_level", "lineno": 47, "end_lineno": 80, "class_name": null}, {"id": "codemarp.views.module_view:_validate_module", "module_id": "codemarp.views.module_view", "name": "_validate_module", "lineno": 14, "end_lineno": 16, "class_name": null}, {"id": "codemarp.views.module_view:module_function_view", "module_id": "codemarp.views.module_view", "name": "module_function_view", "lineno": 6, "end_lineno": 11, "class_name": null}, {"id": "codemarp.views.subgraph:_filter_edges_for_nodes", "module_id": "codemarp.views.subgraph", "name": "_filter_edges_for_nodes", "lineno": 11, "end_lineno": 20, "class_name": null}, {"id": "codemarp.views.subgraph:_modules_for_functions", "module_id": "codemarp.views.subgraph", "name": "_modules_for_functions", "lineno": 23, "end_lineno": 27, "class_name": null}, {"id": "codemarp.views.subgraph:build_function_subgraph", "module_id": "codemarp.views.subgraph", "name": "build_function_subgraph", "lineno": 4, "end_lineno": 8, "class_name": null}, {"id": "codemarp.views.trace:_build_call_adjacency", "module_id": "codemarp.views.trace", "name": "_build_call_adjacency", "lineno": 8, "end_lineno": 14, "class_name": null}, {"id": "codemarp.views.trace:_build_reverse_call_adjacency", "module_id": "codemarp.views.trace", "name": "_build_reverse_call_adjacency", "lineno": 75, "end_lineno": 81, "class_name": null}, {"id": "codemarp.views.trace:_validate_entrypoint", "module_id": "codemarp.views.trace", "name": "_validate_entrypoint", "lineno": 94, "end_lineno": 96, "class_name": null}, {"id": "codemarp.views.trace:reverse_trace_function_view", "module_id": "codemarp.views.trace", "name": "reverse_trace_function_view", "lineno": 84, "end_lineno": 91, "class_name": null}, {"id": "codemarp.views.trace:trace_function_view", "module_id": "codemarp.views.trace", "name": "trace_function_view", "lineno": 42, "end_lineno": 47, "class_name": null}, {"id": "codemarp.views.trace:trace_functions_forward", "module_id": "codemarp.views.trace", "name": "trace_functions_forward", "lineno": 17, "end_lineno": 39, "class_name": null}, {"id": "codemarp.views.trace:trace_functions_reverse", "module_id": "codemarp.views.trace", "name": "trace_functions_reverse", "lineno": 50, "end_lineno": 72, "class_name": null}], "control_flow_nodes": [], "edges": [{"source": "codemarp.analyzers", "target": "codemarp.contracts", "kind": "imports", "metadata": {}, "label": "imports", "reason": null}, {"source": "codemarp.analyzers", "target": "codemarp.graph", "kind": "imports", "metadata": {}, "label": "imports", "reason": null}, {"source": "codemarp.analyzers", "target": "codemarp.parser", "kind": "imports", "metadata": {}, "label": "imports", "reason": null}, {"source": "codemarp.analyzers.high_level:build_high_level_edges", "target": "codemarp.analyzers.high_level:_dedupe_edges", "kind": "calls", "metadata": {}, "label": "calls", "reason": "same_module"}, {"source": "codemarp.analyzers.high_level:build_high_level_edges", "target": "codemarp.analyzers.high_level:_resolve_local_import", "kind": "calls", "metadata": {}, "label": "calls", "reason": "same_module"}, {"source": "codemarp.analyzers.high_level:build_high_level_edges", "target": "codemarp.analyzers.high_level:aggregate_module_id", "kind": "calls", "metadata": {}, "label": "calls", "reason": "same_module"}, {"source": "codemarp.analyzers.low_level:build_low_level_view", "target": "codemarp.parser.python_parser:find_function_node", "kind": "calls", "metadata": {}, "label": "calls", "reason": "imported_symbol"}, {"source": "codemarp.analyzers.mid_level:_resolve_callee", "target": "codemarp.analyzers.mid_level:_resolve_imported_module_call", "kind": "calls", "metadata": {}, "label": "calls", "reason": "same_module"}, {"source": "codemarp.analyzers.mid_level:_resolve_callee", "target": "codemarp.analyzers.mid_level:_resolve_imported_symbol_call", "kind": "calls", "metadata": {}, "label": "calls", "reason": "same_module"}, {"source": "codemarp.analyzers.mid_level:_resolve_callee", "target": "codemarp.analyzers.mid_level:_resolve_same_module_call", "kind": "calls", "metadata": {}, "label": "calls", "reason": "same_module"}, {"source": "codemarp.analyzers.mid_level:_resolve_callee", "target": "codemarp.analyzers.mid_level:_resolve_unique_global_call", "kind": "calls", "metadata": {}, "label": "calls", "reason": "same_module"}, {"source": "codemarp.analyzers.mid_level:_resolve_unique_global_call", "target": "codemarp.analyzers.mid_level:_is_dotted_call", "kind": "calls", "metadata": {}, "label": "calls", "reason": "same_module"}, {"source": "codemarp.analyzers.mid_level:build_mid_level_edges", "target": "codemarp.analyzers.mid_level:_dedupe_edges", "kind": "calls", "metadata": {}, "label": "calls", "reason": "same_module"}, {"source": "codemarp.analyzers.mid_level:build_mid_level_edges", "target": "codemarp.analyzers.mid_level:_resolve_callee", "kind": "calls", "metadata": {}, "label": "calls", "reason": "same_module"}, {"source": "codemarp.cli", "target": "codemarp.analyzers", "kind": "imports", "metadata": {}, "label": "imports", "reason": null}, {"source": "codemarp.cli", "target": "codemarp.errors", "kind": "imports", "metadata": {}, "label": "imports", "reason": null}, {"source": "codemarp.cli", "target": "codemarp.pipeline", "kind": "imports", "metadata": {}, "label": "imports", "reason": null}, {"source": "codemarp.cli.main:analyze_command", "target": "codemarp.analyzers.low_level:build_low_level_view", "kind": "calls", "metadata": {}, "label": "calls", "reason": "imported_symbol"}, {"source": "codemarp.cli.main:analyze_command", "target": "codemarp.pipeline.apply_view:apply_view", "kind": "calls", "metadata": {}, "label": "calls", "reason": "imported_symbol"}, {"source": "codemarp.cli.main:analyze_command", "target": "codemarp.pipeline.build_bundle:build_bundle", "kind": "calls", "metadata": {}, "label": "calls", "reason": "imported_symbol"}, {"source": "codemarp.cli.main:analyze_command", "target": "codemarp.pipeline.export_all:export_all", "kind": "calls", "metadata": {}, "label": "calls", "reason": "imported_symbol"}, {"source": "codemarp.cli.main:analyze_command", "target": "codemarp.pipeline.export_all:export_low_level", "kind": "calls", "metadata": {}, "label": "calls", "reason": "imported_symbol"}, {"source": "codemarp.cli.main:main", "target": "codemarp.cli.main:_validate_analyze_args", "kind": "calls", "metadata": {}, "label": "calls", "reason": "same_module"}, {"source": "codemarp.cli.main:main", "target": "codemarp.cli.main:analyze_command", "kind": "calls", "metadata": {}, "label": "calls", "reason": "same_module"}, {"source": "codemarp.cli.main:main", "target": "codemarp.cli.main:build_parser", "kind": "calls", "metadata": {}, "label": "calls", "reason": "same_module"}, {"source": "codemarp.exporters", "target": "codemarp.analyzers", "kind": "imports", "metadata": {}, "label": "imports", "reason": null}, {"source": "codemarp.exporters", "target": "codemarp.graph", "kind": "imports", "metadata": {}, "label": "imports", "reason": null}, {"source": "codemarp.exporters.mermaid:_collapsed_group_ids", "target": "codemarp.analyzers.high_level:aggregate_module_id", "kind": "calls", "metadata": {}, "label": "calls", "reason": "imported_symbol"}, {"source": "codemarp.exporters.mermaid:export_control_flow", "target": "codemarp.exporters.mermaid:_safe_id", "kind": "calls", "metadata": {}, "label": "calls", "reason": "same_module"}, {"source": "codemarp.exporters.mermaid:export_function_graph", "target": "codemarp.exporters.mermaid:_safe_id", "kind": "calls", "metadata": {}, "label": "calls", "reason": "same_module"}, {"source": "codemarp.exporters.mermaid:export_low_level_graph", "target": "codemarp.exporters.mermaid:_low_level_class_for_kind", "kind": "calls", "metadata": {}, "label": "calls", "reason": "same_module"}, {"source": "codemarp.exporters.mermaid:export_low_level_graph", "target": "codemarp.exporters.mermaid:_safe_id", "kind": "calls", "metadata": {}, "label": "calls", "reason": "same_module"}, {"source": "codemarp.exporters.mermaid:export_low_level_graph", "target": "codemarp.exporters.mermaid:_shape_for_kind", "kind": "calls", "metadata": {}, "label": "calls", "reason": "same_module"}, {"source": "codemarp.exporters.mermaid:export_module_graph", "target": "codemarp.exporters.mermaid:_collapsed_group_ids", "kind": "calls", "metadata": {}, "label": "calls", "reason": "same_module"}, {"source": "codemarp.exporters.mermaid:export_module_graph", "target": "codemarp.exporters.mermaid:_safe_id", "kind": "calls", "metadata": {}, "label": "calls", "reason": "same_module"}, {"source": "codemarp.graph", "target": "codemarp.contracts", "kind": "imports", "metadata": {}, "label": "imports", "reason": null}, {"source": "codemarp.parser", "target": "codemarp.errors", "kind": "imports", "metadata": {}, "label": "imports", "reason": null}, {"source": "codemarp.parser", "target": "codemarp.graph", "kind": "imports", "metadata": {}, "label": "imports", "reason": null}, {"source": "codemarp.parser.python_parser:find_function_node", "target": "codemarp.parser.python_parser:_find_function_in_tree", "kind": "calls", "metadata": {}, "label": "calls", "reason": "same_module"}, {"source": "codemarp.parser.python_parser:find_function_node", "target": "codemarp.parser.python_parser:discover_python_files", "kind": "calls", "metadata": {}, "label": "calls", "reason": "same_module"}, {"source": "codemarp.parser.python_parser:find_function_node", "target": "codemarp.parser.python_parser:module_id_from_path", "kind": "calls", "metadata": {}, "label": "calls", "reason": "same_module"}, {"source": "codemarp.parser.python_parser:find_function_node", "target": "codemarp.parser.python_parser:parse_low_level_focus", "kind": "calls", "metadata": {}, "label": "calls", "reason": "same_module"}, {"source": "codemarp.parser.python_parser:parse_python_file", "target": "codemarp.parser.python_parser:module_id_from_path", "kind": "calls", "metadata": {}, "label": "calls", "reason": "same_module"}, {"source": "codemarp.pipeline", "target": "codemarp.analyzers", "kind": "imports", "metadata": {}, "label": "imports", "reason": null}, {"source": "codemarp.pipeline", "target": "codemarp.exporters", "kind": "imports", "metadata": {}, "label": "imports", "reason": null}, {"source": "codemarp.pipeline", "target": "codemarp.graph", "kind": "imports", "metadata": {}, "label": "imports", "reason": null}, {"source": "codemarp.pipeline", "target": "codemarp.parser", "kind": "imports", "metadata": {}, "label": "imports", "reason": null}, {"source": "codemarp.pipeline", "target": "codemarp.views", "kind": "imports", "metadata": {}, "label": "imports", "reason": null}, {"source": "codemarp.pipeline.apply_view:apply_view", "target": "codemarp.views.module_view:module_function_view", "kind": "calls", "metadata": {}, "label": "calls", "reason": "imported_symbol"}, {"source": "codemarp.pipeline.apply_view:apply_view", "target": "codemarp.views.trace:reverse_trace_function_view", "kind": "calls", "metadata": {}, "label": "calls", "reason": "imported_symbol"}, {"source": "codemarp.pipeline.apply_view:apply_view", "target": "codemarp.views.trace:trace_function_view", "kind": "calls", "metadata": {}, "label": "calls", "reason": "imported_symbol"}, {"source": "codemarp.pipeline.build_bundle:build_bundle", "target": "codemarp.analyzers.high_level:build_high_level_edges", "kind": "calls", "metadata": {}, "label": "calls", "reason": "imported_symbol"}, {"source": "codemarp.pipeline.build_bundle:build_bundle", "target": "codemarp.analyzers.mid_level:build_mid_level_edges", "kind": "calls", "metadata": {}, "label": "calls", "reason": "imported_symbol"}, {"source": "codemarp.pipeline.build_bundle:build_bundle", "target": "codemarp.parser.python_parser:discover_python_files", "kind": "calls", "metadata": {}, "label": "calls", "reason": "imported_symbol"}, {"source": "codemarp.pipeline.build_bundle:build_bundle", "target": "codemarp.parser.python_parser:package_from_module_id", "kind": "calls", "metadata": {}, "label": "calls", "reason": "imported_symbol"}, {"source": "codemarp.pipeline.build_bundle:build_bundle", "target": "codemarp.parser.python_parser:parse_python_file", "kind": "calls", "metadata": {}, "label": "calls", "reason": "imported_symbol"}, {"source": "codemarp.pipeline.export_all:export_all", "target": "codemarp.exporters.json_exporter:export_bundle_json", "kind": "calls", "metadata": {}, "label": "calls", "reason": "imported_symbol"}, {"source": "codemarp.pipeline.export_all:export_all", "target": "codemarp.exporters.mermaid:export_function_graph", "kind": "calls", "metadata": {}, "label": "calls", "reason": "imported_symbol"}, {"source": "codemarp.pipeline.export_all:export_all", "target": "codemarp.exporters.mermaid:export_module_graph", "kind": "calls", "metadata": {}, "label": "calls", "reason": "imported_symbol"}, {"source": "codemarp.pipeline.export_all:export_low_level", "target": "codemarp.exporters.json_exporter:export_bundle_json", "kind": "calls", "metadata": {}, "label": "calls", "reason": "imported_symbol"}, {"source": "codemarp.pipeline.export_all:export_low_level", "target": "codemarp.exporters.mermaid:export_low_level_graph", "kind": "calls", "metadata": {}, "label": "calls", "reason": "imported_symbol"}, {"source": "codemarp.pipeline.export_all:export_low_level", "target": "codemarp.exporters.mermaid:export_module_graph", "kind": "calls", "metadata": {}, "label": "calls", "reason": "imported_symbol"}, {"source": "codemarp.views", "target": "codemarp.errors", "kind": "imports", "metadata": {}, "label": "imports", "reason": null}, {"source": "codemarp.views", "target": "codemarp.graph", "kind": "imports", "metadata": {}, "label": "imports", "reason": null}, {"source": "codemarp.views.module_view:module_function_view", "target": "codemarp.views.module_view:_validate_module", "kind": "calls", "metadata": {}, "label": "calls", "reason": "same_module"}, {"source": "codemarp.views.module_view:module_function_view", "target": "codemarp.views.subgraph:build_function_subgraph", "kind": "calls", "metadata": {}, "label": "calls", "reason": "imported_symbol"}, {"source": "codemarp.views.subgraph:build_function_subgraph", "target": "codemarp.views.subgraph:_filter_edges_for_nodes", "kind": "calls", "metadata": {}, "label": "calls", "reason": "same_module"}, {"source": "codemarp.views.subgraph:build_function_subgraph", "target": "codemarp.views.subgraph:_modules_for_functions", "kind": "calls", "metadata": {}, "label": "calls", "reason": "same_module"}, {"source": "codemarp.views.trace:reverse_trace_function_view", "target": "codemarp.views.subgraph:build_function_subgraph", "kind": "calls", "metadata": {}, "label": "calls", "reason": "imported_symbol"}, {"source": "codemarp.views.trace:reverse_trace_function_view", "target": "codemarp.views.trace:_validate_entrypoint", "kind": "calls", "metadata": {}, "label": "calls", "reason": "same_module"}, {"source": "codemarp.views.trace:reverse_trace_function_view", "target": "codemarp.views.trace:trace_functions_reverse", "kind": "calls", "metadata": {}, "label": "calls", "reason": "same_module"}, {"source": "codemarp.views.trace:trace_function_view", "target": "codemarp.views.subgraph:build_function_subgraph", "kind": "calls", "metadata": {}, "label": "calls", "reason": "imported_symbol"}, {"source": "codemarp.views.trace:trace_function_view", "target": "codemarp.views.trace:_validate_entrypoint", "kind": "calls", "metadata": {}, "label": "calls", "reason": "same_module"}, {"source": "codemarp.views.trace:trace_function_view", "target": "codemarp.views.trace:trace_functions_forward", "kind": "calls", "metadata": {}, "label": "calls", "reason": "same_module"}, {"source": "codemarp.views.trace:trace_functions_forward", "target": "codemarp.views.trace:_build_call_adjacency", "kind": "calls", "metadata": {}, "label": "calls", "reason": "same_module"}, {"source": "codemarp.views.trace:trace_functions_forward", "target": "codemarp.views.trace:_validate_entrypoint", "kind": "calls", "metadata": {}, "label": "calls", "reason": "same_module"}, {"source": "codemarp.views.trace:trace_functions_reverse", "target": "codemarp.views.trace:_build_reverse_call_adjacency", "kind": "calls", "metadata": {}, "label": "calls", "reason": "same_module"}, {"source": "codemarp.views.trace:trace_functions_reverse", "target": "codemarp.views.trace:_validate_entrypoint", "kind": "calls", "metadata": {}, "label": "calls", "reason": "same_module"}]}